{
  "cli": {
    "version": ">= 18.8.1",
    "appVersionSource": "remote"
  },
  "build": {
    "development": {
      "developmentClient": true,
      "distribution": "internal"
    },
    "preview": {
      "distribution": "internal"
    },
    "production": {
      "autoIncrement": true,
      "ios": {
        "uploadSymbols": true
      }
    }
  },
  "submit": {
    "production": {
      "ios": {
        "appleId": "abhinavtej@unifesto.app",
        "ascAppId": "6767165496",
        "appleTeamId": "9AH3Z5C5DH"
      },
      "android": {
        "serviceAccountKeyPath": "./google-play-service-account.json",
        "track": "production"
      }
    }
  }
}